imspy_connector-0.3.23.dist-info/METADATA
imspy_connector-0.3.23.dist-info/WHEEL
imspy_connector/__init__.py
imspy_connector/imspy_connector.cpython-311-darwin.so
imspy_connector-0.3.23.dist-info/RECORD
