Metadata-Version: 2.4
Name: imspy_connector
Version: 0.3.23
Classifier: Programming Language :: Rust
Classifier: Programming Language :: Python :: Implementation :: CPython
Classifier: Programming Language :: Python :: Implementation :: PyPy
Requires-Dist: opentims-bruker-bridge>=1.1.0
Requires-Python: >=3.11
